py3_hello/__init__.py
py3_hello/py3_hello.py
py3_hello-2.0.1.dist-info/METADATA
py3_hello-2.0.1.dist-info/WHEEL
py3_hello-2.0.1.dist-info/entry_points.txt
py3_hello-2.0.1.dist-info/licenses/LICENSE
py3_hello-2.0.1.dist-info/RECORD
