Metadata-Version: 2.1
Name: py3-hello
Version: 2.0.1
Summary: A program to test packaging and deployment
Project-URL: Homepage, https://gitlab.com/jfxs/py3-hello/
Project-URL: Documentation, https://jfxs.gitlab.io/py3-hello/
Author-email: FX Soubirou <soubirou@yahoo.fr>
License: MIT
License-File: LICENSE
Classifier: License :: OSI Approved :: MIT License
Classifier: Operating System :: OS Independent
Classifier: Programming Language :: Python :: 3
Requires-Python: >=3.10
Requires-Dist: click>=8.1.7
